README.rst
setup.py
bin/nanolife
bin/nanolife.bat
nanolife/LifeGame.py
nanolife/__main__.py
nanolife.egg-info/PKG-INFO
nanolife.egg-info/SOURCES.txt
nanolife.egg-info/dependency_links.txt
nanolife.egg-info/not-zip-safe
nanolife.egg-info/requires.txt
nanolife.egg-info/top_level.txt